fstring_to_format/__init__.py
fstring_to_format/__main__.py
fstring_to_format/core.py
fstring_to_format-0.1.2.dist-info/LICENSE
fstring_to_format-0.1.2.dist-info/METADATA
fstring_to_format-0.1.2.dist-info/WHEEL
fstring_to_format-0.1.2.dist-info/top_level.txt
fstring_to_format-0.1.2.dist-info/RECORD
