Metadata-Version: 2.1
Name: fstring-to-format
Version: 0.1.2
Summary: fstring_to_format converts Python f-string expressions to .format() for backwards compatibility.
Home-page: https://github.com/eftalgezer/fstring_to_format
Author: Eftal Gezer
Author-email: eftal.gezer@astrobiyoloji.org
Project-URL: Bug Reports, https://github.com/eftalgezer/fstring_to_format/issues
Project-URL: Source, https://github.com/eftalgezer/fstring_to_format/
Project-URL: Blog, https://beyondthearistotelian.blogspot.com/search/label/fstring_to_format
Project-URL: Developer, https://www.eftalgezer.com/
Keywords: f-string,fstring,format,f-string to format converter,fstring to format converter
Classifier: Development Status :: 5 - Production/Stable
Classifier: Intended Audience :: Developers
Classifier: Intended Audience :: Information Technology
Classifier: Topic :: Software Development
Classifier: Topic :: Utilities
Classifier: Typing :: Typed
Classifier: License :: OSI Approved :: GNU General Public License v3 or later (GPLv3+)
Classifier: Operating System :: MacOS :: MacOS X
Classifier: Operating System :: Microsoft :: Windows
Classifier: Operating System :: POSIX :: Linux
Classifier: Operating System :: OS Independent
Classifier: Programming Language :: Python :: 2.7
Classifier: Programming Language :: Python :: 3
Classifier: Programming Language :: Python :: 3.1
Classifier: Programming Language :: Python :: 3.2
Classifier: Programming Language :: Python :: 3.3
Classifier: Programming Language :: Python :: 3.4
Classifier: Programming Language :: Python :: 3.5
Classifier: Programming Language :: Python :: 3.6
Classifier: Programming Language :: Python :: 3.7
Classifier: Programming Language :: Python :: 3.8
Classifier: Programming Language :: Python :: 3.9
Classifier: Programming Language :: Python :: 3.10
License-File: LICENSE
